dataprocessing/__init__.py
dataprocessing/data-processing-functions.py
dataprocessing/datafunctions.py
ims_data_processing-0.0.116.dist-info/METADATA
ims_data_processing-0.0.116.dist-info/WHEEL
ims_data_processing-0.0.116.dist-info/top_level.txt
ims_data_processing-0.0.116.dist-info/RECORD
