Metadata-Version: 2.1
Name: ims-data-processing
Version: 0.0.116
Summary: IMS Data Processing Package
Author: IMS Cam
Author-email: thecjrobs@gmail.com
Keywords: python,data processing
Classifier: Development Status :: 3 - Alpha
Classifier: Intended Audience :: Developers
Classifier: Programming Language :: Python :: 3
Classifier: Operating System :: Unix
Classifier: Operating System :: MacOS :: MacOS X
Classifier: Operating System :: Microsoft :: Windows
